freq_e/__init__.py
freq_e/ecdf.py
freq_e/estimate.py
freq_e-0.1.1.dist-info/LICENSE
freq_e-0.1.1.dist-info/METADATA
freq_e-0.1.1.dist-info/WHEEL
freq_e-0.1.1.dist-info/top_level.txt
freq_e-0.1.1.dist-info/RECORD
