Metadata-Version: 2.1
Name: freq-e
Version: 0.1.1
Summary: Class frequency estimation
Home-page: https://github.com/slanglab/freq-e
Author: Katherine Keith and Brendan O'Connor
Author-email: kkeith@cs.umass.edu
License: UNKNOWN
Platform: UNKNOWN
Classifier: Programming Language :: Python :: 3
Classifier: License :: OSI Approved :: MIT License
Classifier: Operating System :: OS Independent
